benchmark_apis/__init__.py
benchmark_apis/abstract_api.py
benchmark_apis/hpo/abstract_bench.py
benchmark_apis/hpo/continuous_search_spaces.json
benchmark_apis/hpo/dataset_names.json
benchmark_apis/hpo/discrete_search_spaces.json
benchmark_apis/hpo/fidel_spaces.json
benchmark_apis/hpo/hpobench.py
benchmark_apis/hpo/hpolib.py
benchmark_apis/hpo/jahs.py
benchmark_apis/hpo/lcbench.py
benchmark_apis/hpo/lcbench_dataset_ids.json
benchmark_apis/synthetic/abstract_func.py
benchmark_apis/synthetic/branin.py
benchmark_apis/synthetic/hartmann.py
mfhpo_benchmark_api-2.2.2.dist-info/LICENSE
mfhpo_benchmark_api-2.2.2.dist-info/METADATA
mfhpo_benchmark_api-2.2.2.dist-info/WHEEL
mfhpo_benchmark_api-2.2.2.dist-info/top_level.txt
mfhpo_benchmark_api-2.2.2.dist-info/RECORD
